python_hmac_auth/__init__.py
python_hmac_auth/hmac_auth.py
python_hmac_auth-0.4.dist-info/DESCRIPTION.rst
python_hmac_auth-0.4.dist-info/METADATA
python_hmac_auth-0.4.dist-info/metadata.json
python_hmac_auth-0.4.dist-info/RECORD
python_hmac_auth-0.4.dist-info/top_level.txt
python_hmac_auth-0.4.dist-info/WHEEL
