Metadata-Version: 1.1
Name: python-hmac-auth
Version: 0.4
Summary: Python client for jersey-hmac-auth (https://github.com/bazaarvoice/jersey-hmac-auth)
Home-page: https://github.com/bazaarvoice/python-hmac-auth
Author: Bazaarvoice
Author-email: benton.porter@bazaarvoice.com
License: 
